testntmemapi/__init__.py
testntmemapi/libs/simdkmp.dll
testntmemapi/misc.py
testntmemapi-1.0.0.dist-info/METADATA
testntmemapi-1.0.0.dist-info/WHEEL
testntmemapi-1.0.0.dist-info/RECORD
