Metadata-Version: 2.3
Name: testntmemapi
Version: 1.0.0
Summary: Simple library for Windows to manipulate process virtual memory with stelthy syscall wraps
Author: Xenely
Requires-Python: >=3.10
Classifier: Programming Language :: Python :: 3
Classifier: Programming Language :: Python :: 3.10
Classifier: Programming Language :: Python :: 3.11
Classifier: Programming Language :: Python :: 3.12
Classifier: Programming Language :: Python :: 3.13
